ivc/__init__.py
ivc/algorithms.py
ivc/utils.py
iterative_voting_consensus-0.1.2.dist-info/METADATA
iterative_voting_consensus-0.1.2.dist-info/WHEEL
iterative_voting_consensus-0.1.2.dist-info/RECORD
